{
    "asset": {
        "format": "jpg",
        "id": "4c9c4bd787ef1031caf3da49c6f9735a",
        "name": "0132_05835_b.jpg",
        "path": "file:C:/Users/truon/Downloads/GreenParking/0132_05835_b.jpg",
        "size": {
            "width": 472,
            "height": 303
        },
        "state": 2,
        "type": 1
    },
    "regions": [
        {
            "id": "mtdB-pOGL",
            "type": "RECTANGLE",
            "tags": [
                "license_Plate"
            ],
            "boundingBox": {
                "height": 80.01298701298703,
                "width": 88.56150104239055,
                "left": 228.51737317581654,
                "top": 91.16233766233766
            },
            "points": [
                {
                    "x": 228.51737317581654,
                    "y": 91.16233766233766
                },
                {
                    "x": 317.0788742182071,
                    "y": 91.16233766233766
                },
                {
                    "x": 317.0788742182071,
                    "y": 171.1753246753247
                },
                {
                    "x": 228.51737317581654,
                    "y": 171.1753246753247
                }
            ]
        }
    ],
    "version": "2.1.0"
}