{
    "asset": {
        "format": "jpg",
        "id": "6a987fb7835c592101db53fac7cf11bf",
        "name": "0047_00970_b.jpg",
        "path": "file:C:/Users/truon/Downloads/GreenParking/0047_00970_b.jpg",
        "size": {
            "width": 472,
            "height": 303
        },
        "state": 2,
        "type": 1
    },
    "regions": [
        {
            "id": "5-ls03KD2",
            "type": "RECTANGLE",
            "tags": [
                "license_Plate"
            ],
            "boundingBox": {
                "height": 62.30519480519481,
                "width": 71.50521195274496,
                "left": 184.72863099374567,
                "top": 153.1396103896104
            },
            "points": [
                {
                    "x": 184.72863099374567,
                    "y": 153.1396103896104
                },
                {
                    "x": 256.23384294649065,
                    "y": 153.1396103896104
                },
                {
                    "x": 256.23384294649065,
                    "y": 215.4448051948052
                },
                {
                    "x": 184.72863099374567,
                    "y": 215.4448051948052
                }
            ]
        }
    ],
    "version": "2.1.0"
}