{
    "asset": {
        "format": "jpg",
        "id": "a2ca3619042484414562535c48f1e455",
        "name": "0139_09523_b.jpg",
        "path": "file:C:/Users/truon/Downloads/GreenParking/0139_09523_b.jpg",
        "size": {
            "width": 472,
            "height": 303
        },
        "state": 2,
        "type": 1
    },
    "regions": [
        {
            "id": "IR2GOu8vF",
            "type": "RECTANGLE",
            "tags": [
                "license_Plate"
            ],
            "boundingBox": {
                "height": 76.73376623376625,
                "width": 94.13759555246699,
                "left": 151.1080611535789,
                "top": 127.23376623376625
            },
            "points": [
                {
                    "x": 151.1080611535789,
                    "y": 127.23376623376625
                },
                {
                    "x": 245.24565670604588,
                    "y": 127.23376623376625
                },
                {
                    "x": 245.24565670604588,
                    "y": 203.9675324675325
                },
                {
                    "x": 151.1080611535789,
                    "y": 203.9675324675325
                }
            ]
        }
    ],
    "version": "2.1.0"
}