{
    "asset": {
        "format": "jpg",
        "id": "e2352f08c88a710171bdf720fbea82b9",
        "name": "0147_04452_b.jpg",
        "path": "file:C:/Users/truon/Downloads/GreenParking/0147_04452_b.jpg",
        "size": {
            "width": 472,
            "height": 303
        },
        "state": 2,
        "type": 1
    },
    "regions": [
        {
            "id": "fE3gO1c5t",
            "type": "RECTANGLE",
            "tags": [
                "license_Plate"
            ],
            "boundingBox": {
                "height": 80.3409090909091,
                "width": 82.00138985406532,
                "left": 224.25330090340515,
                "top": 96.40909090909092
            },
            "points": [
                {
                    "x": 224.25330090340515,
                    "y": 96.40909090909092
                },
                {
                    "x": 306.2546907574705,
                    "y": 96.40909090909092
                },
                {
                    "x": 306.2546907574705,
                    "y": 176.75
                },
                {
                    "x": 224.25330090340515,
                    "y": 176.75
                }
            ]
        }
    ],
    "version": "2.1.0"
}